PySeqTools/PySeqTools.py
PySeqTools/__init__.py
PySeqTools/reference.txt
PySeqTools/.ipynb_checkpoints/PySeqTools-checkpoint.py
PySeqTools/.ipynb_checkpoints/__init__-checkpoint.py
PySeqTools/.ipynb_checkpoints/reference-checkpoint.txt
PySeqTools/html/PySeqTools.html
PySeqTools/html/.ipynb_checkpoints/PySeqTools-checkpoint.html
pyseqtools-0.1.5.dist-info/METADATA
pyseqtools-0.1.5.dist-info/WHEEL
pyseqtools-0.1.5.dist-info/licenses/LICENSE
pyseqtools-0.1.5.dist-info/RECORD
