Metadata-Version: 2.1
Name: PySeqTools
Version: 0.1.5
Summary: a python package for sequence alignment, simulation and visulization
Project-URL: Homepage, https://gitlab.bucknell.edu/jc092/doc_networks
Project-URL: Bug Tracker, https://gitlab.bucknell.edu/jc092/doc_networks/-/issues
Author-email: Jeffrey Cai <jc092@bucknell.edu>
License-File: LICENSE
Classifier: License :: OSI Approved :: MIT License
Classifier: Operating System :: OS Independent
Classifier: Programming Language :: Python :: 3
Requires-Python: >=3.7
